odoo/addons/stock_release_channel_partner_by_date_delivery_window/README.rst
odoo/addons/stock_release_channel_partner_by_date_delivery_window/__init__.py
odoo/addons/stock_release_channel_partner_by_date_delivery_window/__manifest__.py
odoo/addons/stock_release_channel_partner_by_date_delivery_window/i18n/it.po
odoo/addons/stock_release_channel_partner_by_date_delivery_window/i18n/stock_release_channel_partner_by_date_delivery_window.pot
odoo/addons/stock_release_channel_partner_by_date_delivery_window/readme/CONTRIBUTORS.rst
odoo/addons/stock_release_channel_partner_by_date_delivery_window/readme/DESCRIPTION.rst
odoo/addons/stock_release_channel_partner_by_date_delivery_window/static/description/icon.png
odoo/addons/stock_release_channel_partner_by_date_delivery_window/static/description/index.html
odoo/addons/stock_release_channel_partner_by_date_delivery_window/tests/__init__.py
odoo/addons/stock_release_channel_partner_by_date_delivery_window/tests/test_release_channel_partner_date.py
odoo_addon_stock_release_channel_partner_by_date_delivery_window-16.0.1.0.0.3.dist-info/METADATA
odoo_addon_stock_release_channel_partner_by_date_delivery_window-16.0.1.0.0.3.dist-info/WHEEL
odoo_addon_stock_release_channel_partner_by_date_delivery_window-16.0.1.0.0.3.dist-info/top_level.txt
odoo_addon_stock_release_channel_partner_by_date_delivery_window-16.0.1.0.0.3.dist-info/RECORD
